code/__init__.py
case_study-0.0.1.dist-info/METADATA
case_study-0.0.1.dist-info/WHEEL
case_study-0.0.1.dist-info/top_level.txt
case_study-0.0.1.dist-info/RECORD
