Metadata-Version: 2.1
Name: case-study
Version: 0.0.1
Summary: Functions used in a case study
Home-page: https://github.com/pypa/sampleproject
Author: Ibon Tamayo
Author-email: itamuria@gmail.com
License: UNKNOWN
Platform: UNKNOWN
Classifier: Programming Language :: Python :: 3
Classifier: License :: OSI Approved :: MIT License
Classifier: Operating System :: OS Independent
